robyn/__init__.py
robyn/__main__.py
robyn/ai.py
robyn/argument_parser.py
robyn/authentication.py
robyn/cli.py
robyn/dependency_injection.py
robyn/env_populator.py
robyn/events.py
robyn/exceptions.py
robyn/jsonify.py
robyn/logger.py
robyn/mcp.py
robyn/openapi.py
robyn/processpool.py
robyn/py.typed
robyn/reloader.py
robyn/responses.py
robyn/robyn.cpython-314-darwin.so
robyn/robyn.pyi
robyn/router.py
robyn/scaffold/mongo/Dockerfile
robyn/scaffold/mongo/app.py
robyn/scaffold/mongo/requirements.txt
robyn/scaffold/no-db/Dockerfile
robyn/scaffold/no-db/app.py
robyn/scaffold/no-db/requirements.txt
robyn/scaffold/postgres/Dockerfile
robyn/scaffold/postgres/app.py
robyn/scaffold/postgres/requirements.txt
robyn/scaffold/postgres/supervisord.conf
robyn/scaffold/prisma/Dockerfile
robyn/scaffold/prisma/app.py
robyn/scaffold/prisma/requirements.txt
robyn/scaffold/prisma/schema.prisma
robyn/scaffold/sqlalchemy/Dockerfile
robyn/scaffold/sqlalchemy/__init__.py
robyn/scaffold/sqlalchemy/app.py
robyn/scaffold/sqlalchemy/models.py
robyn/scaffold/sqlalchemy/requirements.txt
robyn/scaffold/sqlite/Dockerfile
robyn/scaffold/sqlite/app.py
robyn/scaffold/sqlite/requirements.txt
robyn/scaffold/sqlmodel/Dockerfile
robyn/scaffold/sqlmodel/app.py
robyn/scaffold/sqlmodel/models.py
robyn/scaffold/sqlmodel/requirements.txt
robyn/status_codes.py
robyn/swagger.html
robyn/templating.py
robyn/types.py
robyn/ws.py
robyn-0.76.0.dist-info/METADATA
robyn-0.76.0.dist-info/WHEEL
robyn-0.76.0.dist-info/entry_points.txt
robyn-0.76.0.dist-info/licenses/LICENSE
robyn-0.76.0.dist-info/RECORD
