Metadata-Version: 2.4
Name: robyn
Version: 0.76.0
Classifier: Development Status :: 3 - Alpha
Classifier: Environment :: Web Environment
Classifier: Intended Audience :: Developers
Classifier: License :: OSI Approved :: BSD License
Classifier: Operating System :: OS Independent
Classifier: Topic :: Internet :: WWW/HTTP
Classifier: Programming Language :: Python :: 3
Classifier: Programming Language :: Python :: 3.10
Classifier: Programming Language :: Python :: 3.11
Classifier: Programming Language :: Python :: 3.12
Classifier: Programming Language :: Python :: 3.13
Classifier: Programming Language :: Python :: 3.14
Classifier: Programming Language :: Python :: Implementation :: CPython
Requires-Dist: inquirerpy==0.3.4
Requires-Dist: multiprocess==0.70.14
Requires-Dist: orjson>=3.11.5,<4.0.0
Requires-Dist: rustimport==1.3.4
Requires-Dist: uvloop~=0.22.1 ; platform_machine != 'armv7l' and platform_python_implementation == 'CPython' and sys_platform != 'win32'
Requires-Dist: watchdog==4.0.1
Requires-Dist: jinja2==3.0.1 ; extra == 'templating'
Provides-Extra: templating
License-File: LICENSE
Summary: A Super Fast Async Python Web Framework with a Rust runtime.
Home-Page: https://github.com/sparckles/robyn
Author-email: Sanskar Jethi <sansyrox@gmail.com>
Project-URL: Changelog, https://github.com/sparckles/robyn/blob/main/CHANGELOG.md
Project-URL: Documentation, https://robyn.tech/
Project-URL: Issues, https://github.com/sparckles/robyn/issues
Project-URL: Repository, https://github.com/sparckles/robyn
